lnurl/__init__.py
lnurl/cli.py
lnurl/core.py
lnurl/exceptions.py
lnurl/helpers.py
lnurl/models.py
lnurl/py.typed
lnurl/types.py
lnurl-0.8.3.dist-info/LICENSE
lnurl-0.8.3.dist-info/METADATA
lnurl-0.8.3.dist-info/WHEEL
lnurl-0.8.3.dist-info/entry_points.txt
lnurl-0.8.3.dist-info/RECORD
