Metadata-Version: 2.3
Name: lnurl
Version: 0.8.3
Summary: LNURL implementation for Python.
License: MIT
Author: Alan Bits
Author-email: alan@lnbits.com
Requires-Python: >=3.10
Classifier: License :: OSI Approved :: MIT License
Classifier: Programming Language :: Python :: 3
Classifier: Programming Language :: Python :: 3.10
Classifier: Programming Language :: Python :: 3.11
Classifier: Programming Language :: Python :: 3.12
Classifier: Programming Language :: Python :: 3.13
Requires-Dist: bech32
Requires-Dist: bip32 (>=4.0,<5.0)
Requires-Dist: bolt11
Requires-Dist: ecdsa
Requires-Dist: httpx
Requires-Dist: pycryptodomex (>=3.21.0,<4.0.0)
Requires-Dist: pydantic (>=1,<2)
